catvibes/__init__.py
catvibes/__main__.py
catvibes/catvibes_lib.py
catvibes/config
catvibes/qt_gui.py
catvibes/term_ui.py
Catvibes-1.0.22.dist-info/LICENSE
Catvibes-1.0.22.dist-info/METADATA
Catvibes-1.0.22.dist-info/WHEEL
Catvibes-1.0.22.dist-info/entry_points.txt
Catvibes-1.0.22.dist-info/top_level.txt
Catvibes-1.0.22.dist-info/RECORD
