Metadata-Version: 2.1
Name: Catvibes
Version: 1.0.22
Summary: A musicplayer with a terminal and a Qt frontend
License: GNU GENERAL PUBLIC LICENSE
Project-URL: Hompage, https://github.com/12fab4/Catvibes
Requires-Python: >=3.11
License-File: LICENSE
Requires-Dist: yt-dlp >=2023.11.16
Requires-Dist: ytmusicapi >=1.3.2
Requires-Dist: eyed3 >=0.9.7
Requires-Dist: PyQt6 >=6.6.1
Requires-Dist: playsound >=1.3.0
Requires-Dist: python-vlc >=3.0.20123
Requires-Dist: windows-curses >=2.3.2 ; sys_platform == "win32"
